pycdp/__init__.py
pycdp-0.2.0.dist-info/METADATA
pycdp-0.2.0.dist-info/WHEEL
pycdp-0.2.0.dist-info/RECORD
