Metadata-Version: 2.1
Name: pycdp
Version: 0.2.0
Summary: The coolest Python wrapper for CDP the is :)
License: MIT
Author: shner-elmo
Author-email: 770elmo@gmail.com
Requires-Python: >=3.10,<4.0
Classifier: License :: OSI Approved :: MIT License
Classifier: Programming Language :: Python :: 3
Classifier: Programming Language :: Python :: 3.10
Classifier: Programming Language :: Python :: 3.11
